climetlab_maelstrom_nogwd/__init__.py
climetlab_maelstrom_nogwd/nogwd.py
climetlab_maelstrom_nogwd-0.2.0.dist-info/LICENSE
climetlab_maelstrom_nogwd-0.2.0.dist-info/METADATA
climetlab_maelstrom_nogwd-0.2.0.dist-info/WHEEL
climetlab_maelstrom_nogwd-0.2.0.dist-info/entry_points.txt
climetlab_maelstrom_nogwd-0.2.0.dist-info/top_level.txt
climetlab_maelstrom_nogwd-0.2.0.dist-info/zip-safe
climetlab_maelstrom_nogwd-0.2.0.dist-info/RECORD
