Metadata-Version: 2.1
Name: climetlab-maelstrom-nogwd
Version: 0.2.0
Summary: A dataset plugin for climetlab for the dataset maelstrom-nogwd.
Home-page: https://git.ecmwf.int/projects/MLFET/repos/maelstrom-nogwd
Author: Matthew Chantry
Author-email: matthew.chantry@ecmwf.int
License: Apache License Version 2.0
Keywords: meteorology
Platform: UNKNOWN
Classifier: Development Status :: 3 - Alpha
Classifier: Intended Audience :: Developers
Classifier: License :: OSI Approved :: Apache Software License
Classifier: Programming Language :: Python :: 3
Classifier: Programming Language :: Python :: 3.6
Classifier: Programming Language :: Python :: 3.7
Classifier: Programming Language :: Python :: 3.8
Classifier: Programming Language :: Python :: 3.9
Classifier: Programming Language :: Python :: Implementation :: CPython
Classifier: Programming Language :: Python :: Implementation :: PyPy
Classifier: Operating System :: OS Independent
License-File: LICENSE
Requires-Dist: climetlab (>=0.8.9)
